CONTRIBUTORS.txt
LICENSE.txt
index.html
setup.py
webprocessingserver.cfg
wps.cgi
wps.fcgi
wps_http_server.py
wps_install_config.py
WPServer.egg-info/PKG-INFO
WPServer.egg-info/SOURCES.txt
WPServer.egg-info/dependency_links.txt
WPServer.egg-info/not-zip-safe
WPServer.egg-info/top_level.txt
WebProcessingServer/Exceptions.py
WebProcessingServer/Handlers.py
WebProcessingServer/Server.py
WebProcessingServer/__init__.py
WebProcessingServer/Action/Noop.py
WebProcessingServer/Action/OGRGeos.py
WebProcessingServer/Action/Reproject.py
WebProcessingServer/Action/Routing.py
WebProcessingServer/Action/Shapely.py
WebProcessingServer/Action/Simplify.py
WebProcessingServer/Action/__init__.py
WebProcessingServer/Action/ogrhelpers.py
WebProcessingServer/Service/REST.py
WebProcessingServer/Service/__init__.py
algorithms/Douglas-Peucker.txt
doc/Readme.txt
img/move_vertex_off.png
img/move_vertex_on.png
img/select_feature_off.png
img/select_feature_on.png
vectorformats/Feature.py
vectorformats/__init__.py
vectorformats/Formats/Format.py
vectorformats/Formats/GeoJSON.py
vectorformats/Formats/GeoRSS.py
vectorformats/Formats/HTML.py
vectorformats/Formats/KML.py
vectorformats/Formats/OGR.py
vectorformats/Formats/WFS.py
vectorformats/Formats/WKT.py
vectorformats/Formats/__init__.py
