Metadata-Version: 1.0
Name: WPServer
Version: 1.0
Summary: a web mapping transformation library
Home-page: http://code.google.com/p/webprocessingserver/
Author: Christohper Schmidt
Author-email: crschmidt@crschmidt.net
License: Clear BSD
Platform: UNKNOWN
Classifier: Development Status :: 4 - Beta
Classifier: Intended Audience :: Developers
Classifier: Intended Audience :: Science/Research
Classifier: Operating System :: OS Independent
Classifier: Programming Language :: Python
Classifier: Topic :: Scientific/Engineering :: GIS
